[
    {
        "name" : "WeatherApp",
        "imgURL": "./images/weatherApp.jpg",
        "description" : "A customisable weather application for smartphones.",
        "skills": "Preact, JavaScipt, CSS",
        "projectURL": "#/weatherapp"
    },

    {
        "name": "Trie Data Structure",
        "imgURL": "./images/triedata.png",
        "description": "A data structure designed to allow operations on millions of stored words in extremly small times.",
        "skills": "Java",
        "projectURL": "#/triedata"
    },

    {
        "name": "Final Year Project",
        "imgURL": "./images/fyproject.jpg",
        "description": "A research study into how colours affect a players perception of characters in video games.",
        "skills": "C#, Unity, Java",
        "projectURL": "#/fyproject"
    },

    {
        "name": "Dumesq",
        "imgURL": "./images/dumesq.png",
        "description": "A third person shooter with a 2D artstyle and randomly generated levels.",
        "skills": "C#, Unity, Blender",
        "projectURL": "#/dumesq"
    },

    

    {
        "name": "Source Map Creation",
        "imgURL": "./images/mapmod.png",
        "description": "Lorem ipsum dolor sit amet, consectetur adipiscing elit, sed do eiusmod tempor incididunt ut labore et dolore magna aliqua. Ut enim ad minim veniam, quis nostrud exercitation ullamco laboris nisi ut aliquip ex ea commodo consequat. Duis aute irure dolor in reprehenderit in voluptate velit esse cillum dolore eu fugiat nulla pariatur. Excepteur sint occaecat cupidatat non proident, sunt in culpa qui officia deserunt mollit anim id est laborum.",
        "skills": "Valve Hammer Editor",
        "projectURL": "#/maps"
    }


]
